smart_analytica/__init__.py
smart_analytica/viewer.py
smart_analytica-0.1.0.dist-info/licenses/LICENSE
smart_analytica-0.1.0.dist-info/METADATA
smart_analytica-0.1.0.dist-info/WHEEL
smart_analytica-0.1.0.dist-info/top_level.txt
smart_analytica-0.1.0.dist-info/RECORD
